MANIFEST.in
README.md
setup.py
vc/__init__.py
vc/create.py
vc/utils.py
vc.egg-info/PKG-INFO
vc.egg-info/SOURCES.txt
vc.egg-info/dependency_links.txt
vc.egg-info/requires.txt
vc.egg-info/top_level.txt
vc/fonts/ChalkboardSE-Light.ttf
vc/fonts/PrincetownStd.otf
vc/fonts/londrina-solid.ttf