Metadata-Version: 1.0
Name: vc
Version: 2018.7.10
Summary: a library for create verification-code
Home-page: https://github.com/kylescript/vc
Author: kyle
Author-email: kyle.script@gmail.com
License: MIT License
Keywords: verification code
Platform: any
